fspathtree/__init__.py
fspathtree/fspathtree.py
fspathtree-1.1.1.dist-info/METADATA
fspathtree-1.1.1.dist-info/WHEEL
fspathtree-1.1.1.dist-info/licenses/LICENSE.txt
fspathtree-1.1.1.dist-info/RECORD
