Metadata-Version: 2.3
Name: fspathtree
Version: 1.1.1
Summary: A small utility for wrapping trees (nested dict/list) that allows filesystem-like path access, including walking up with "../".
Author-email: CD Clark III <clifton.clark@gmail.com>
Requires-Python: >=3.8
